zenconfig/__init__.py
zenconfig/base.py
zenconfig/encoder.py
zenconfig/formats/__init__.py
zenconfig/formats/json.py
zenconfig/formats/toml.py
zenconfig/formats/yaml.py
zenconfig/py.typed
zenconfig/read.py
zenconfig/schemas/__init__.py
zenconfig/schemas/attrs.py
zenconfig/schemas/dataclass.py
zenconfig/schemas/dict.py
zenconfig/schemas/pydantic.py
zenconfig/write.py
zenconfig-2.2.0.dist-info/licenses/LICENSE
zenconfig-2.2.0.dist-info/WHEEL
zenconfig-2.2.0.dist-info/METADATA
zenconfig-2.2.0.dist-info/RECORD
