Metadata-Version: 2.4
Name: zenconfig
Version: 2.2.0
Summary: Simple configuration loader for python.
Author: Gabriel Pajot
Author-email: Gabriel Pajot <gab@lescactus.eu>
License-Expression: MIT
License-File: LICENSE
Requires-Dist: typing-extensions>=4.10
Requires-Dist: attrs>=22.2,<26 ; extra == 'attrs'
Requires-Dist: pydantic>=1,<3 ; extra == 'pydantic'
Requires-Dist: tomlkit>=0,<1 ; extra == 'toml'
Requires-Dist: pyyaml>=6,<7 ; extra == 'yaml'
Requires-Python: >=3.10
Project-URL: repository, https://github.com/gpajot/zen-config
Provides-Extra: attrs
Provides-Extra: pydantic
Provides-Extra: toml
Provides-Extra: yaml
